README.md
setup.py
aioecobee/__init__.py
aioecobee/const.py
aioecobee/ecobee.py
aioecobee/errors.py
aioecobee/sensor.py
aioecobee/thermostat.py
aioecobee.egg-info/PKG-INFO
aioecobee.egg-info/SOURCES.txt
aioecobee.egg-info/dependency_links.txt
aioecobee.egg-info/requires.txt
aioecobee.egg-info/top_level.txt