Metadata-Version: 2.1
Name: aioecobee
Version: 0.1.0
Summary: Python3 async library for interacting with the ecobee API
Home-page: https://github.com/marthoc/aioecobee
Author: Mark Coombes
Author-email: mark@markcoombes.ca
License: UNKNOWN
Platform: UNKNOWN
Classifier: Intended Audience :: Developers
Classifier: Programming Language :: Python
Classifier: Programming Language :: Python :: 3
Classifier: License :: OSI Approved :: MIT License
Classifier: Operating System :: OS Independent
Classifier: Topic :: Software Development :: Libraries :: Python Modules
